{
  "id": "mofcom-unreliable-entity-list",
  "label": "中国商務部 不可靠実体清単",
  "generated": "2026-07-13T10:49:13.098Z",
  "resolvedUrl": "https://www.mofcom.gov.cn/zcfb/dwmygl/",
  "lines": [
    "政策发布",
    "部令公告",
    "规范性文件",
    "综合政策",
    "国内贸易管理",
    "稳外贸稳外资政策措施",
    "对外贸易管理",
    "服务贸易",
    "公平贸易",
    "外国投资管理",
    "对外经济技术合作",
    "对外贸易管理",
    "var authorizedReadUnitId = \"712985f61f1a45c1b250eb08a6102b5d\";",
    "政策解读",
    "国家发展改革委、商务部有关负责人就《扩大消费“十五五”规划》答记者问",
    "[政策原文]",
    "[2026-07-13]",
    "商务部流通发展司负责人解读《关于加快零售业创新发展的意见》",
    "[政策原文]",
    "[2026-07-09]",
    "盛秋平副部长出席国新办发布会介绍全链条扩大汽车消费有关情况",
    "[政策原文]",
    "[政策原文]",
    "[2026-06-23]",
    "凌激副部长兼国际贸易谈判副代表出席国新办发布会介绍利用外资固稳促优有关政策措施",
    "[政策原文]",
    "[2026-06-22]",
    "市场建设司负责人解读《关于加快“人工智能+消费”发展的实施意见》",
    "[政策原文]",
    "[2026-06-18]",
    "商务部服贸司负责人解读《关于促进铁路与旅游融合发展 扩大服务消费的若干措施》",
    "[政策原文]",
    "[2026-06-10]",
    "盛秋平副部长出席国新办发布会介绍加力优化离境退税措施扩大入境消费有关情况",
    "[政策原文]",
    "[2026-05-18]",
    "商务部服贸司负责人解读《服务贸易标准化工作行动计划（2026—2030年）》",
    "[政策原文]",
    "[2026-04-23]",
    ".columnTitle_01 h3{border-bottom:0;}"
  ]
}
